nstoolspack/__init__.py
nstoolspack/zhtools/__init__.py
nstoolspack/zhtools/langconv.py
nstoolspack/zhtools/zh_wiki.py
nstoolspack-0.0.1.dist-info/LICENSE
nstoolspack-0.0.1.dist-info/METADATA
nstoolspack-0.0.1.dist-info/WHEEL
nstoolspack-0.0.1.dist-info/top_level.txt
nstoolspack-0.0.1.dist-info/RECORD
